date2cron/__init__.py
date2cron/date2cron.py
date2cron-0.1dev_r0.dist-info/DESCRIPTION.rst
date2cron-0.1dev_r0.dist-info/METADATA
date2cron-0.1dev_r0.dist-info/RECORD
date2cron-0.1dev_r0.dist-info/WHEEL
date2cron-0.1dev_r0.dist-info/metadata.json
date2cron-0.1dev_r0.dist-info/top_level.txt
date2cron-0.1dev_r0.dist-info/zip-safe
