Metadata-Version: 2.0
Name: date2cron
Version: 0.1dev-r0
Summary: date2cron
Home-page: https://bitbucket.org/yafeile/date2cron
Author: yafeile
Author-email: yafeile@sohu.com
License: UNKNOWN
Keywords: cron
Platform: UNKNOWN
